device.v
module device (
    input clk,
    input reset,
    input tx_start,
    input [7:0] tx_data,
    output reg tx_active,
    output reg tx_done,
    output reg serial_tx,
    input serial_rx,
    output reg [7:0] rx_data,
    output reg rx_valid
);

parameter IDLE = 0;
parameter START = 1;
parameter DATA = 2;
parameter STOP = 3;
parameter DONE = 4;

reg [2:0] tx_state;
reg [2:0] rx_state;
reg [2:0] tx_bit;
reg [2:0] rx_bit;
reg [7:0] tx_reg;
reg [7:0] rx_reg;


always @(posedge clk or posedge reset) begin
    if (reset) begin
        tx_state <= IDLE;
        tx_bit <= 0;
        tx_reg <= 0;
        tx_active <= 0;
        tx_done <= 0;
        serial_tx <= 1;
    end
    else begin
        tx_done <= 0;
            
        case (tx_state)
            IDLE: begin
                tx_active <= 0;
                serial_tx <= 1;//Initial value
                tx_bit <= 0;

                if (tx_start) begin
                    tx_reg <= tx_data;
                    tx_active <= 1;
                    serial_tx <= 0; //The start bit is sent
                    tx_state <= START;
                end
            end

            START: begin
                serial_tx <= tx_reg[0];
                tx_reg <= tx_reg >> 1;
                tx_bit <= 1;
                tx_state <= DATA;
            end

            DATA: begin
                serial_tx <= tx_reg[0];
                tx_reg <= tx_reg >> 1;

                if (tx_bit == 7) begin
                    tx_state <= STOP;
                end
                else begin
                    tx_bit <= tx_bit + 1;
                end
            end

            STOP: begin
                serial_tx <= 1; //The stop bit is sent
                tx_state <= DONE;
            end

            DONE: begin
                tx_active <= 0;
                tx_done <= 1;
                tx_state <= IDLE;
            end

            default: begin
                tx_state <= IDLE;
            end

        endcase
    end
end


always @(posedge clk or posedge reset) begin
    if (reset) begin
        rx_state <= IDLE;
        rx_bit <= 0;
        rx_reg <= 0;
        rx_data <= 0;
        rx_valid <= 0;
    end
    else begin
        rx_valid <= 0;

        case (rx_state)
            IDLE: begin
                rx_bit <= 0;

                if (serial_rx == 0) begin //To check if start bit was received
                    rx_reg <= 0;
                    rx_state <= START;
                end
            end

            START: begin
                rx_reg <= {serial_rx, rx_reg[7:1]};
                rx_bit <= 1;
                rx_state <= DATA;
            end

            DATA: begin
                rx_reg <= {serial_rx, rx_reg[7:1]};

                if (rx_bit == 7) begin
                    rx_state <= STOP;
                end
                else begin
                    rx_bit <= rx_bit + 1;
                end
            end

            STOP: begin
                if (serial_rx == 1) //To check if the stop bit is received
                    rx_state <= DONE;
                else
                    rx_state <= IDLE;
            end

            DONE: begin
                rx_data <= rx_reg;
                rx_valid <= 1;
                rx_state <= IDLE;
            end

            default: begin
                rx_state <= IDLE;
            end

        endcase
    end
end

endmodule

uart_tb.v
`timescale 1ns/1ps

module uart_tb;

parameter BAUD_RATE = 115200;
parameter TX_DATA1 = 8'hA5;
parameter TX_DATA2 = 8'h3C;

reg clk;
reg reset;
reg tx_start1;
reg tx_start2;

wire tx_active1;
wire tx_done1;
wire serial_tx1;
wire [7:0] rx_data1;
wire rx_valid1;

wire tx_active2;
wire tx_done2;
wire serial_tx2;
wire [7:0] rx_data2;
wire rx_valid2;

real HALF_PERIOD;

device d1 (
    .clk(clk),
    .reset(reset),
    .tx_start(tx_start1),
    .tx_data(TX_DATA1),
    .tx_active(tx_active1),
    .tx_done(tx_done1),
    .serial_tx(serial_tx1),
    .serial_rx(serial_tx2),
    .rx_data(rx_data1),
    .rx_valid(rx_valid1)
);

device d2 (
    .clk(clk),
    .reset(reset),
    .tx_start(tx_start2),
    .tx_data(TX_DATA2),
    .tx_active(tx_active2),
    .tx_done(tx_done2),
    .serial_tx(serial_tx2),
    .serial_rx(serial_tx1),
    .rx_data(rx_data2),
    .rx_valid(rx_valid2)
);

initial begin
    clk = 0;
    HALF_PERIOD = 1000000000.0 / (2.0 * BAUD_RATE);

    forever #(HALF_PERIOD) clk = ~clk;
end

initial begin
   $dumpfile("uart.vcd");
   $dumpvars(0, uart_tb);
    reset = 1;
    tx_start1 = 0;
    tx_start2 = 0;

    #100;
    reset = 0;

    @(posedge clk);

    tx_start1 = 1;
    tx_start2 = 1;

    @(posedge clk);

    tx_start1 = 0;
    tx_start2 = 0;

    wait(rx_valid1 && rx_valid2);

    $display("Device 1 transmitted = %h", TX_DATA1);
    $display("Device 2 received    = %h", rx_data2);

    $display("Device 2 transmitted = %h", TX_DATA2);
    $display("Device 1 received    = %h", rx_data1);

    #100;

    $finish;
end

endmodule

uart.vcd
$date
	Tue Jul 21 00:26:44 2026
$end
$version
	Icarus Verilog
$end
$timescale
	1ps
$end
$scope module uart_tb $end
$var wire 1 ! tx_done2 $end
$var wire 1 " tx_done1 $end
$var wire 1 # tx_active2 $end
$var wire 1 $ tx_active1 $end
$var wire 1 % serial_tx2 $end
$var wire 1 & serial_tx1 $end
$var wire 1 ' rx_valid2 $end
$var wire 1 ( rx_valid1 $end
$var wire 8 ) rx_data2 [7:0] $end
$var wire 8 * rx_data1 [7:0] $end
$var parameter 32 + BAUD_RATE $end
$var parameter 8 , TX_DATA1 $end
$var parameter 8 - TX_DATA2 $end
$var reg 1 . clk $end
$var reg 1 / reset $end
$var reg 1 0 tx_start1 $end
$var reg 1 1 tx_start2 $end
$var real 1 2 HALF_PERIOD $end
$scope module d1 $end
$var wire 1 . clk $end
$var wire 1 / reset $end
$var wire 8 3 tx_data [7:0] $end
$var wire 1 0 tx_start $end
$var wire 1 % serial_rx $end
$var parameter 32 4 DATA $end
$var parameter 32 5 DONE $end
$var parameter 32 6 IDLE $end
$var parameter 32 7 START $end
$var parameter 32 8 STOP $end
$var reg 3 9 rx_bit [2:0] $end
$var reg 8 : rx_data [7:0] $end
$var reg 8 ; rx_reg [7:0] $end
$var reg 3 < rx_state [2:0] $end
$var reg 1 ( rx_valid $end
$var reg 1 & serial_tx $end
$var reg 1 $ tx_active $end
$var reg 3 = tx_bit [2:0] $end
$var reg 1 " tx_done $end
$var reg 8 > tx_reg [7:0] $end
$var reg 3 ? tx_state [2:0] $end
$upscope $end
$scope module d2 $end
$var wire 1 . clk $end
$var wire 1 / reset $end
$var wire 1 & serial_rx $end
$var wire 8 @ tx_data [7:0] $end
$var wire 1 1 tx_start $end
$var parameter 32 A DATA $end
$var parameter 32 B DONE $end
$var parameter 32 C IDLE $end
$var parameter 32 D START $end
$var parameter 32 E STOP $end
$var reg 3 F rx_bit [2:0] $end
$var reg 8 G rx_data [7:0] $end
$var reg 8 H rx_reg [7:0] $end
$var reg 3 I rx_state [2:0] $end
$var reg 1 ' rx_valid $end
$var reg 1 % serial_tx $end
$var reg 1 # tx_active $end
$var reg 3 J tx_bit [2:0] $end
$var reg 1 ! tx_done $end
$var reg 8 K tx_reg [7:0] $end
$var reg 3 L tx_state [2:0] $end
$upscope $end
$upscope $end
$enddefinitions $end
$comment Show the parameter values. $end
$dumpall
b11 E
b1 D
b0 C
b100 B
b10 A
b11 8
b1 7
b0 6
b100 5
b10 4
b111100 -
b10100101 ,
b11100001000000000 +
$end
#0
$dumpvars
b0 L
b0 K
b0 J
b0 I
b0 H
b0 G
b0 F
b111100 @
b0 ?
b0 >
b0 =
b0 <
b0 ;
b0 :
b0 9
b10100101 3
r4340.277777777777 2
01
00
1/
0.
b0 *
b0 )
0(
0'
1&
1%
0$
0#
0"
0!
$end
#100000
0/
#4340278
b1 L
0%
1#
b111100 K
b1 ?
0&
1$
b10100101 >
11
10
1.
#8680556
0.
#13020834
b10 ?
b1 =
b1010010 >
1&
b1 <
b10 L
b1 J
b11110 K
b1 I
01
00
1.
#17361112
0.
#21701390
b10 I
b1 F
b10000000 H
b10 J
b1111 K
b10 <
b1 9
b10 =
b101001 >
0&
1.
#26041668
0.
#30381946
b11 =
b10100 >
1&
b10 9
b11 J
b111 K
1%
b10 F
b1000000 H
1.
#34722224
0.
#39062502
b11 F
b10100000 H
b100 J
b11 K
b11 9
b10000000 ;
b100 =
b1010 >
0&
1.
#43402780
0.
#47743058
b101 =
b101 >
b100 9
b11000000 ;
b101 J
b1 K
b100 F
b1010000 H
1.
#52083336
0.
#56423614
b101 F
b101000 H
b110 J
b0 K
b101 9
b11100000 ;
b110 =
b10 >
1&
1.
#60763892
0.
#65104170
b111 =
b1 >
0&
b110 9
b11110000 ;
b111 J
0%
b110 F
b10010100 H
1.
#69444448
0.
#73784726
b111 F
b1001010 H
b11 L
b111 9
b1111000 ;
b11 ?
b0 >
1&
1.
#78125004
0.
#82465282
b100 ?
b11 <
b111100 ;
b100 L
1%
b11 I
b10100101 H
1.
#86805560
0.
#91145838
b100 I
b0 L
1!
0#
b100 <
b0 ?
1"
0$
1.
#95486116
0.
#99826394
b0 =
0"
b0 <
1(
b111100 *
b111100 :
b0 J
0!
b0 I
1'
b10100101 )
b10100101 G
1.
